intervals/__init__.py
intervals/exc.py
intervals/interval.py
intervals/parser.py
intervals-0.9.2.dist-info/LICENSE
intervals-0.9.2.dist-info/METADATA
intervals-0.9.2.dist-info/WHEEL
intervals-0.9.2.dist-info/top_level.txt
intervals-0.9.2.dist-info/RECORD
